jbeep/jbeep.py
jbeep-1.3.dist-info/DESCRIPTION.rst
jbeep-1.3.dist-info/METADATA
jbeep-1.3.dist-info/RECORD
jbeep-1.3.dist-info/WHEEL
jbeep-1.3.dist-info/metadata.json
jbeep-1.3.dist-info/top_level.txt
