Metadata-Version: 2.0
Name: jbeep
Version: 1.3
Summary: A simple alert and timer
Home-page: https://github.com/jayhhwang/jbeep
Author: Jay Hwang
Author-email: thebluebirdspeaks@gmail.com
License: UNKNOWN
Platform: UNKNOWN
